utilities_hki/__init__.py
utilities_hki/analy_utils.py
utilities_hki/date_utils.py
utilities_hki/db_utils.py
utilities_hki/email_utils.py
utilities_hki/fb_utils.py
utilities_hki/google_sheet.py
utilities_hki/privacy_utils.py
utilities_hki/data/gmm_2022-10-23.joblib
utilities_hki/data/gmm_2023-04-02.joblib
utilities_hki/data/gmm_scaler_2022-10-23.joblib
utilities_hki/data/gmm_scaler_2023-04-02.joblib
utilities_hki-0.1.24.dist-info/METADATA
utilities_hki-0.1.24.dist-info/WHEEL
utilities_hki-0.1.24.dist-info/entry_points.txt
utilities_hki-0.1.24.dist-info/license_files/LICENSE.txt
utilities_hki-0.1.24.dist-info/RECORD
