Metadata-Version: 2.1
Name: utilities-hki
Version: 0.1.24
Summary: Global utilities for Humankind data science
Project-URL: Homepage, https://github.com/humankind-datascience/utilities-hki
Author: Francisco Pena, Colleen Treado
Classifier: License :: OSI Approved :: GNU Affero General Public License v3
Classifier: Operating System :: OS Independent
Classifier: Programming Language :: Python :: 3
Requires-Python: >=3.7
Requires-Dist: gspread
Requires-Dist: joblib==1.2.0
Requires-Dist: numpy
Requires-Dist: oauth2client
Requires-Dist: pandas
Requires-Dist: pandas-market-calendars
Requires-Dist: psycopg2-binary>2.8
Requires-Dist: pytz
